kursachrestoran/__init__.py
kursachrestoran/database.py
kursachrestoran-0.1.dist-info/METADATA
kursachrestoran-0.1.dist-info/WHEEL
kursachrestoran-0.1.dist-info/top_level.txt
kursachrestoran-0.1.dist-info/RECORD
