Metadata-Version: 2.2
Name: kursachrestoran
Version: 0.1
Summary: A library for interacting with a PostgreSQL database for restaurant management
Home-page: https://github.com/yourusername/kursachrestoran
Author: Your Name
Author-email: your.email@example.com
Classifier: Programming Language :: Python :: 3
Classifier: License :: OSI Approved :: MIT License
Classifier: Operating System :: OS Independent
Requires-Python: >=3.6
Requires-Dist: psycopg2
Dynamic: author
Dynamic: author-email
Dynamic: classifier
Dynamic: description-content-type
Dynamic: home-page
Dynamic: requires-dist
Dynamic: requires-python
Dynamic: summary
